app_configs/__init__.py
app_configs/config_manager.py
bodega_bot/__init__.py
bodega_bot/app.py
bodega_bot/bodega_bot.py
bodega_bot/version.py
db/__init__.py
db/db.py
discord_analytics/__init__.py
discord_analytics/analytics_engine.py
libdisc/__init__.py
libdisc/colorstr.py
libdisc/database_manager.py
libdisc/discord_manager.py
libdisc/media_manager.py
libdisc/plot_manager.py
libdisc/dataclasses/__init__.py
libdisc/dataclasses/discord_objects.py
libdisc/models/__init__.py
libdisc/models/base_mixin.py
libdisc/models/gif.py
libdisc/models/message.py
libdisc/models/user.py
bodega_bot-0.0.3.dist-info/LICENSE
bodega_bot-0.0.3.dist-info/METADATA
bodega_bot-0.0.3.dist-info/WHEEL
bodega_bot-0.0.3.dist-info/entry_points.txt
bodega_bot-0.0.3.dist-info/top_level.txt
bodega_bot-0.0.3.dist-info/RECORD
