Metadata-Version: 2.1
Name: bodega-bot
Version: 0.0.3
Summary: bodega-bot is a Discord bot that can be configured to monitor and produce humorous analytics for Discord channels.
Home-page: https://github.com/UltimoBodega/discord_analytics
Author: Ultimo Bodega
Author-email: ultimobodega@gmail.com
License: Public domain
Keywords: Discord,bot,monitor,analytics,humorous,quotes,channel
Platform: UNKNOWN
Requires-Dist: SQLAlchemy (==1.3.22)
Requires-Dist: aiohttp (==3.6.3)
Requires-Dist: async-timeout (==3.0.1)
Requires-Dist: attrs (==20.3.0)
Requires-Dist: beautifulsoup4 (==4.8.2)
Requires-Dist: certifi (==2020.12.5)
Requires-Dist: chardet (==3.0.4)
Requires-Dist: cycler (==0.10.0)
Requires-Dist: discord.py (==1.5.1)
Requires-Dist: flake8 (==3.8.4)
Requires-Dist: giphy-client (==1.0.0)
Requires-Dist: idna (==2.10)
Requires-Dist: kiwisolver (==1.3.1)
Requires-Dist: lxml (==4.6.2)
Requires-Dist: matplotlib (==3.3.3)
Requires-Dist: multidict (==4.7.6)
Requires-Dist: mypy (==0.790)
Requires-Dist: numpy (==1.19.4)
Requires-Dist: progressbar (==2.5)
Requires-Dist: pyparsing (==2.4.7)
Requires-Dist: python-dateutil (==2.8.1)
Requires-Dist: scipy (==1.6.0)
Requires-Dist: six (==1.15.0)
Requires-Dist: soupsieve (==2.0.1)
Requires-Dist: typing-extensions (==3.7.4.3)
Requires-Dist: wincertstore (==0.2)
Requires-Dist: yarl (==1.5.1)
